nonebot_plugin_nokia/__init__.py
nonebot_plugin_nokia/nokia.py
nonebot_plugin_nokia/res/font.ttf
nonebot_plugin_nokia/res/img.png
nonebot_plugin_nokia-0.0.3.dist-info/LICENSE
nonebot_plugin_nokia-0.0.3.dist-info/WHEEL
nonebot_plugin_nokia-0.0.3.dist-info/METADATA
nonebot_plugin_nokia-0.0.3.dist-info/RECORD
